progbg/__init__.py
progbg/__main__.py
progbg/cli.py
progbg/core.py
progbg/globals.py
progbg/graphing.py
progbg/parsers.py
progbg/style.py
progbg/subr.py
progbg/util.py
progbg/serve/__init__.py
progbg/serve/templates/bar_data.html
progbg/serve/templates/base.html
progbg/serve/templates/index.html
progbg/serve/templates/line_data.html
progbg-0.3.dist-info/LICENSE
progbg-0.3.dist-info/METADATA
progbg-0.3.dist-info/WHEEL
progbg-0.3.dist-info/entry_points.txt
progbg-0.3.dist-info/top_level.txt
progbg-0.3.dist-info/RECORD
