Metadata-Version: 2.1
Name: progbg
Version: 0.3
Summary: A programmable way help quickly run and produce benchmarks and create graphs
Home-page: https://github.com/krhancoc/progbg
Author: Kenneth R Hancock
Author-email: krhancoc@uwaterloo.ca
License: MIT
Keywords: benchmark,graph
Platform: UNKNOWN
Classifier: Programming Language :: Python :: 3
Classifier: Topic :: System :: Benchmark
Classifier: Operating System :: OS Independent
Requires-Python: >=3.8
Requires-Dist: numpy
Requires-Dist: matplotlib
Requires-Dist: flask
Requires-Dist: pandas
